femethods/__init__.py
femethods/elements.py
femethods/loads.py
femethods/mesh.py
femethods/reactions.py
femethods/core/__init__.py
femethods/core/_base_elements.py
femethods/core/_common.py
tests/__init__.py
tests/functional tests/__init__.py
tests/functional tests/settings.py
tests/functional tests/test_fixed_support_beams.py
tests/functional tests/test_simply_supported_beam.py
tests/functional tests/validate.py
femethods-0.1.7a2.dist-info/METADATA
femethods-0.1.7a2.dist-info/WHEEL
femethods-0.1.7a2.dist-info/top_level.txt
femethods-0.1.7a2.dist-info/RECORD
