Metadata-Version: 2.1
Name: femethods
Version: 0.1.7a2
Summary: Implementation of Finite Element Analysis
Home-page: https://femethods.readthedocs.io/en/latest/index.html
Author: Joseph Contreras
Author-email: 26684136+JosephJContreras@users.noreply.github.com
License: UNKNOWN
Platform: UNKNOWN
Classifier: Programming Language :: Python :: 3
Classifier: License :: OSI Approved :: MIT License
Classifier: Operating System :: OS Independent
Requires-Dist: numpy
Requires-Dist: matplotlib
Requires-Dist: scipy
